[
  {
    "student_id": "STU-001",
    "isActive": false,
    "admission_date": "31-04-2024",
    "username": "Aarav Sharma",
    "fatherName": "Rajesh Sharma",
    "course_name": "BCA",
    "rollNumber": "10A01",
    "totalFees": 5000,
    "paidFees": 2500,
    "remainingFees": 2500,
    "gender": "Male",
    "status": "unpaid"
  },
  {
    "student_id": "STU-002",
    "isActive": true,
    "admission_date": "31-04-2025",
    "username": "Pranshi Singh",
    "fatherName": "Sandeep Singh",
    "course_name": "CCC",
    "rollNumber": "12B05",
    "totalFees": 7000,
    "paidFees": 3000,
    "remainingFees": 4000,
    "gender": "Female",
    "status": "unpaid"
  },
  {
    "student_id": "STU-003",
    "isActive": true,
    "admission_date": "31-04-2025",
    "username": "Aditya Gupta",
    "fatherName": "Manoj Gupta",
    "course_name": "O'Level",
    "rollNumber": "11C12",
    "totalFees": 6000,
    "paidFees": 6000,
    "remainingFees": 0,
    "gender": "Male",
    "status": "paid"
  },
  {
    "student_id": "STU-004",
    "isActive": false,
    "admission_date": "31-04-2024",
    "username": "Arjun Kumar",
    "fatherName": "Pramod Kumar",
    "course_name": "B.Tech",
    "rollNumber": "9A21",
    "totalFees": 4000,
    "paidFees": 1000,
    "remainingFees": 3000,
    "gender": "Male",
    "status": "unpaid"
  },
  {
    "student_id": "STU-005",
    "isActive": false,
    "admission_date": "31-04-2024",
    "username": "Sai Patel",
    "fatherName": "Jignesh Patel",
    "course_name": "B.Sc",
    "rollNumber": "10B15",
    "totalFees": 5000,
    "paidFees": 5000,
    "remainingFees": 0,
    "gender": "Male",
    "status": "paid"
  },
  {
    "student_id": "STU-006",
    "isActive": false,
    "admission_date": "31-04-2024",
    "username": "Reyansh Reddy",
    "fatherName": "Srinivas Reddy",
    "course_name": "Nercing",
    "rollNumber": "12A03",
    "totalFees": 7000,
    "paidFees": 6500,
    "remainingFees": 500,
    "gender": "Male",
    "status": "pending"
  },
  {
    "student_id": "STU-007",
    "isActive": false,
    "admission_date": "31-04-2024",
    "username": "Krishna Nair",
    "fatherName": "Gopalakrishnan Nair",
    "course_name": "11th",
    "rollNumber": "11B08",
    "totalFees": 6000,
    "paidFees": 2000,
    "remainingFees": 4000,
    "gender": "Male",
    "status": "unpaid"
  },
  {
    "student_id": "STU-008",
    "isActive": false,
    "admission_date": "31-04-2024",
    "username": "Ishaan Iyer",
    "fatherName": "Subramanian Iyer",
    "course_name": "9th",
    "rollNumber": "9C30",
    "totalFees": 4000,
    "paidFees": 4000,
    "remainingFees": 0,
    "gender": "Female",
    "status": "paid"
  },
  {
    "student_id": "STU-009",
    "isActive": false,
    "admission_date": "31-04-2024",
    "username": "Vihaan Malhotra",
    "fatherName": "Vivek Malhotra",
    "course_name": "BCA",
    "rollNumber": "10C22",
    "totalFees": 5000,
    "paidFees": 1500,
    "remainingFees": 3500,
    "gender": "Male",
    "status": "unpaid"
  },
  {
    "student_id": "STU-010",
    "isActive": false,
    "admission_date": "31-04-2024",
    "username": "Ansh Joshi",
    "fatherName": "Alok Joshi",
    "course_name": "12th",
    "rollNumber": "12C18",
    "totalFees": 7000,
    "paidFees": 7000,
    "remainingFees": 0,
    "gender": "Male",
    "status": "paid"
  },

  {
    "student_id": "STU-001",
    "isActive": false,
    "admission_date": "31-04-2024",
    "username": "Aarav Sharma",
    "fatherName": "Rajesh Sharma",
    "course_name": "BCA",
    "rollNumber": "10A01",
    "totalFees": 5000,
    "paidFees": 2500,
    "remainingFees": 2500,
    "gender": "Male",
    "status": "unpaid"
  },
  {
    "student_id": "STU-002",
    "isActive": true,
    "admission_date": "31-04-2025",
    "username": "Vivaan Singh",
    "fatherName": "Sandeep Singh",
    "course_name": "12th",
    "rollNumber": "12B05",
    "totalFees": 7000,
    "paidFees": 3000,
    "remainingFees": 4000,
    "gender": "Male",
    "status": "unpaid"
  },
  {
    "student_id": "STU-003",
    "isActive": true,
    "admission_date": "31-04-2025",
    "username": "Aditya Gupta",
    "fatherName": "Manoj Gupta",
    "course_name": "11th",
    "rollNumber": "11C12",
    "totalFees": 6000,
    "paidFees": 6000,
    "remainingFees": 0,
    "gender": "Male",
    "status": "paid"
  },
  {
    "student_id": "STU-004",
    "isActive": false,
    "admission_date": "31-04-2024",
    "username": "Arjun Kumar",
    "fatherName": "Pramod Kumar",
    "course_name": "9th",
    "rollNumber": "9A21",
    "totalFees": 4000,
    "paidFees": 1000,
    "remainingFees": 3000,
    "gender": "Male",
    "status": "unpaid"
  },
  {
    "student_id": "STU-005",
    "isActive": false,
    "admission_date": "31-04-2024",
    "username": "Sai Patel",
    "fatherName": "Jignesh Patel",
    "course_name": "BCA",
    "rollNumber": "10B15",
    "totalFees": 5000,
    "paidFees": 5000,
    "remainingFees": 0,
    "gender": "Male",
    "status": "paid"
  },
  {
    "student_id": "STU-006",
    "isActive": false,
    "admission_date": "31-04-2024",
    "username": "Reyansh Reddy",
    "fatherName": "Srinivas Reddy",
    "course_name": "12th",
    "rollNumber": "12A03",
    "totalFees": 7000,
    "paidFees": 6500,
    "remainingFees": 500,
    "gender": "Male",
    "status": "pending"
  },
  {
    "student_id": "STU-007",
    "isActive": false,
    "admission_date": "31-04-2024",
    "username": "Krishna Nair",
    "fatherName": "Gopalakrishnan Nair",
    "course_name": "11th",
    "rollNumber": "11B08",
    "totalFees": 6000,
    "paidFees": 2000,
    "remainingFees": 4000,
    "gender": "Male",
    "status": "unpaid"
  },
  {
    "student_id": "STU-008",
    "isActive": false,
    "admission_date": "31-04-2024",
    "username": "Ishaan Iyer",
    "fatherName": "Subramanian Iyer",
    "course_name": "9th",
    "rollNumber": "9C30",
    "totalFees": 4000,
    "paidFees": 4000,
    "remainingFees": 0,
    "gender": "Male",
    "status": "paid"
  },
  {
    "student_id": "STU-009",
    "isActive": false,
    "admission_date": "31-04-2024",
    "username": "Vihaan Malhotra",
    "fatherName": "Vivek Malhotra",
    "course_name": "BCA",
    "rollNumber": "10C22",
    "totalFees": 5000,
    "paidFees": 1500,
    "remainingFees": 3500,
    "gender": "Male",
    "status": "unpaid"
  },
  {
    "student_id": "STU-010",
    "isActive": false,
    "admission_date": "31-04-2024",
    "username": "Ansh Joshi",
    "fatherName": "Alok Joshi",
    "course_name": "12th",
    "rollNumber": "12C18",
    "totalFees": 7000,
    "paidFees": 7000,
    "remainingFees": 0,
    "gender": "Male",
    "status": "paid"
  }
]
